[
  {
    "name": "Angle Converter",
    "description": "Convert between degrees, radians, gradians, and more.",
    "url": "https://calculatorbit.com/convert/angle/"
  },
  {
    "name": "Area Converter",
    "description": "Convert between square meters, acres, hectares, and more.",
    "url": "https://calculatorbit.com/convert/area/"
  },
  {
    "name": "Data Storage Converter",
    "description": "Convert between bytes, kilobytes, megabytes, gigabytes, etc.",
    "url": "https://calculatorbit.com/convert/data-storage/"
  },
  {
    "name": "Energy Converter",
    "description": "Convert between joules, watt-hours, BTU, and more.",
    "url": "https://calculatorbit.com/convert/energy/"
  },
  {
    "name": "Force Converter",
    "description": "Convert between newtons, pound-force, kilogram-force, and more.",
    "url": "https://calculatorbit.com/convert/force/"
  },
  {
    "name": "Length Converter",
    "description": "Convert between meters, feet, inches, kilometers, miles, and more.",
    "url": "https://calculatorbit.com/convert/length/"
  },
  {
    "name": "Weight Converter",
    "description": "Convert between kilograms, pounds, ounces, grams, and more.",
    "url": "https://calculatorbit.com/convert/weight/"
  },
  {
    "name": "Power Converter",
    "description": "Convert between watts, kilowatts, horsepower, etc.",
    "url": "https://calculatorbit.com/convert/power/"
  },
  {
    "name": "Pressure Converter",
    "description": "Convert between pascals, bars, atmospheres, PSI, and more.",
    "url": "https://calculatorbit.com/convert/pressure/"
  },
  {
    "name": "Temperature Converter",
    "description": "Convert between Celsius, Fahrenheit, Kelvin, etc.",
    "url": "https://calculatorbit.com/convert/temperature/"
  },
  {
    "name": "Time Converter",
    "description": "Convert between seconds, minutes, hours, days, and more.",
    "url": "https://calculatorbit.com/convert/time/"
  },
  {
    "name": "Volume Converter",
    "description": "Convert between liters, gallons, cubic meters, fluid ounces, etc.",
    "url": "https://calculatorbit.com/convert/volume/"
  }
]